.gitignore
README.rst
TODO.txt
bootstrap.py
buildout-withoutgit.cfg
buildout.cfg
kgs.cfg
minitage.cfg
pyramid.cfg
repoze.bfg.kgs.cfg
setup.py
svnignore.sh
docs/CHANGES.txt
docs/INSTALL.rst
selenium/minitage.selenium
selenium/minitagefull.selenium
selenium/withoutminitage.selenium
selenium/withoutminitagefull.selenium
src/collective/__init__.py
src/collective.generic.webbuilder.egg-info/PKG-INFO
src/collective.generic.webbuilder.egg-info/SOURCES.txt
src/collective.generic.webbuilder.egg-info/dependency_links.txt
src/collective.generic.webbuilder.egg-info/entry_points.txt
src/collective.generic.webbuilder.egg-info/namespace_packages.txt
src/collective.generic.webbuilder.egg-info/not-zip-safe
src/collective.generic.webbuilder.egg-info/requires.txt
src/collective.generic.webbuilder.egg-info/top_level.txt
src/collective/generic/__init__.py
src/collective/generic/webbuilder/__init__.py
src/collective/generic/webbuilder/build_index.py
src/collective/generic/webbuilder/cgwb.ini
src/collective/generic/webbuilder/configure.zcml
src/collective/generic/webbuilder/django.zcml
src/collective/generic/webbuilder/interfaces.py
src/collective/generic/webbuilder/meta.zcml
src/collective/generic/webbuilder/models.py
src/collective/generic/webbuilder/paster.py
src/collective/generic/webbuilder/plone3.zcml
src/collective/generic/webbuilder/plone4.zcml
src/collective/generic/webbuilder/plone41.zcml
src/collective/generic/webbuilder/plugins.py
src/collective/generic/webbuilder/pyramid.zcml
src/collective/generic/webbuilder/utils.py
src/collective/generic/webbuilder/views.py
src/collective/generic/webbuilder/webserver.py
src/collective/generic/webbuilder/zcml.py
src/collective/generic/webbuilder/templates/collect.pt
src/collective/generic/webbuilder/templates/index.pt
src/collective/generic/webbuilder/templates/main_template.pt
src/collective/generic/webbuilder/templates/process.pt
src/collective/generic/webbuilder/templates/static/makina.css
src/collective/generic/webbuilder/templates/static/images/disk.png
src/collective/generic/webbuilder/templates/static/images/download.jpg
src/collective/generic/webbuilder/templates/static/images/error.png
src/collective/generic/webbuilder/templates/static/images/favicon.ico
src/collective/generic/webbuilder/templates/static/images/googles.png
src/collective/generic/webbuilder/templates/static/images/link_icon.gif
src/collective/generic/webbuilder/templates/static/images/logo.png
src/collective/generic/webbuilder/tests/egg/src/cgwb.tp.egg-info/PKG-INFO
src/collective/generic/webbuilder/tests/egg/src/cgwb.tp.egg-info/SOURCES.txt
src/collective/generic/webbuilder/tests/egg/src/cgwb.tp.egg-info/dependency_links.txt
src/collective/generic/webbuilder/tests/egg/src/cgwb.tp.egg-info/entry_points.txt
src/collective/generic/webbuilder/tests/egg/src/cgwb.tp.egg-info/namespace_packages.txt
src/collective/generic/webbuilder/tests/egg/src/cgwb.tp.egg-info/not-zip-safe
src/collective/generic/webbuilder/tests/egg/src/cgwb.tp.egg-info/requires.txt
src/collective/generic/webbuilder/tests/egg/src/cgwb.tp.egg-info/top_level.txt
