Metadata-Version: 1.0
Name: collective.generic.webbuilder
Version: 1.1
Summary: Yet another WSGI Paste factory for paste by Makina Corpus
Home-page: http://pypi.python.org/pypi/collective.generic.webbuilder
Author: Mathieu Pasquet, Jean-Philippe Camguilhem
Author-email: kiorky@cryptelium.net, jean-philippe.camguilhem@makina-corpus.com
License: BSD
Platform: UNKNOWN
Classifier: Programming Language :: Python
Classifier: Topic :: Software Development :: Libraries :: Python Modules
